{
    "blockly": false,
    "blockly_xml": "<xml></xml>",
    "category": "Uncategorized",
    "coa": {
        "data": {
            "description": "",
            "edges": [
                {
                    "id": "port_0_to_port_2",
                    "sourceNode": "0",
                    "sourcePort": "0_out",
                    "targetNode": "2",
                    "targetPort": "2_in"
                },
                {
                    "id": "port_2_to_port_3",
                    "sourceNode": "2",
                    "sourcePort": "2_out",
                    "targetNode": "3",
                    "targetPort": "3_in"
                },
                {
                    "id": "port_3_to_port_4",
                    "sourceNode": "3",
                    "sourcePort": "3_out",
                    "targetNode": "4",
                    "targetPort": "4_in"
                },
                {
                    "conditions": [
                        {
                            "index": 0
                        }
                    ],
                    "id": "port_4_to_port_5",
                    "sourceNode": "4",
                    "sourcePort": "4_out",
                    "targetNode": "5",
                    "targetPort": "5_in"
                },
                {
                    "id": "port_5_to_port_6",
                    "sourceNode": "5",
                    "sourcePort": "5_out",
                    "targetNode": "6",
                    "targetPort": "6_in"
                },
                {
                    "id": "port_6_to_port_8",
                    "sourceNode": "6",
                    "sourcePort": "6_out",
                    "targetNode": "8",
                    "targetPort": "8_in"
                },
                {
                    "id": "port_8_to_port_9",
                    "sourceNode": "8",
                    "sourcePort": "8_out",
                    "targetNode": "9",
                    "targetPort": "9_in"
                },
                {
                    "id": "port_9_to_port_10",
                    "sourceNode": "9",
                    "sourcePort": "9_out",
                    "targetNode": "10",
                    "targetPort": "10_in"
                }
            ],
            "hash": "722c7dad41d2f65d2d776c16c6cdf5c22bde6158",
            "nodes": {
                "0": {
                    "data": {
                        "advanced": {
                            "join": []
                        },
                        "functionName": "on_start",
                        "id": "0",
                        "type": "start"
                    },
                    "errors": {},
                    "id": "0",
                    "type": "start",
                    "warnings": {},
                    "x": 1000,
                    "y": 419.9999999999998
                },
                "1": {
                    "data": {
                        "advanced": {
                            "join": []
                        },
                        "functionName": "on_finish",
                        "id": "1",
                        "type": "end"
                    },
                    "errors": {},
                    "id": "1",
                    "type": "end",
                    "warnings": {},
                    "x": 1020,
                    "y": 2040
                },
                "10": {
                    "data": {
                        "action": "update event",
                        "actionType": "generic",
                        "advanced": {
                            "join": []
                        },
                        "connector": "Splunk",
                        "connectorConfigs": [
                            "splunk_instructor"
                        ],
                        "connectorId": "91883aa8-9c81-470b-97a1-5d8f7995f560",
                        "connectorVersion": "v1",
                        "functionId": 1,
                        "functionName": "update_event_1",
                        "id": "10",
                        "loop": {
                            "enabled": false,
                            "exitAfterUnit": "m",
                            "exitAfterValue": 10,
                            "exitConditionEnabled": false,
                            "exitLoopAfter": 2,
                            "pauseUnit": "m",
                            "pauseValue": 2
                        },
                        "parameters": {
                            "comment": "format_4:formatted_data",
                            "event_ids": "artifact:*.cef.event_id",
                            "status": "in progress",
                            "urgency": "critical"
                        },
                        "requiredParameters": [
                            {
                                "data_type": "string",
                                "field": "event_ids"
                            }
                        ],
                        "type": "action"
                    },
                    "errors": {},
                    "id": "10",
                    "type": "action",
                    "warnings": {},
                    "x": 1000,
                    "y": 1784.5
                },
                "2": {
                    "data": {
                        "advanced": {
                            "join": []
                        },
                        "functionId": 1,
                        "functionName": "format_1",
                        "id": "2",
                        "parameters": [
                            "artifact:*.cef.destination"
                        ],
                        "template": "demo server=\"{0}\"\n",
                        "type": "format"
                    },
                    "errors": {},
                    "id": "2",
                    "type": "format",
                    "warnings": {},
                    "x": 980,
                    "y": 560
                },
                "3": {
                    "data": {
                        "action": "run query",
                        "actionType": "investigate",
                        "advanced": {
                            "join": []
                        },
                        "connector": "Splunk",
                        "connectorConfigs": [
                            "splunk_instructor"
                        ],
                        "connectorId": "91883aa8-9c81-470b-97a1-5d8f7995f560",
                        "connectorVersion": "v1",
                        "functionId": 1,
                        "functionName": "run_query_1",
                        "id": "3",
                        "loop": {
                            "enabled": false,
                            "exitAfterUnit": "m",
                            "exitAfterValue": 10,
                            "exitConditionEnabled": false,
                            "exitLoopAfter": 2,
                            "pauseUnit": "m",
                            "pauseValue": 2
                        },
                        "parameters": {
                            "command": "savedsearch",
                            "query": "format_1:formatted_data",
                            "search_mode": "smart"
                        },
                        "requiredParameters": [
                            {
                                "data_type": "string",
                                "field": "query"
                            },
                            {
                                "data_type": "string",
                                "default": "search",
                                "field": "command"
                            },
                            {
                                "data_type": "string",
                                "default": "smart",
                                "field": "search_mode"
                            }
                        ],
                        "type": "action"
                    },
                    "errors": {},
                    "id": "3",
                    "type": "action",
                    "warnings": {},
                    "x": 980,
                    "y": 720
                },
                "4": {
                    "data": {
                        "advanced": {
                            "join": []
                        },
                        "conditions": [
                            {
                                "comparisons": [
                                    {
                                        "conditionIndex": 0,
                                        "op": "==",
                                        "param": "run_query_1:action_result.data.*.priority",
                                        "value": "high"
                                    }
                                ],
                                "conditionIndex": 0,
                                "logic": "and"
                            }
                        ],
                        "customDatapaths": {
                            "run_query_1": {
                                "action_result.data.*.peer": {
                                    "contains": [],
                                    "isCustomDatapath": true,
                                    "label": "action_result.data.*.peer",
                                    "value": "run_query_1:action_result.data.*.peer"
                                },
                                "action_result.data.*.priority": {
                                    "contains": [],
                                    "isCustomDatapath": true,
                                    "label": "action_result.data.*.priority",
                                    "value": "run_query_1:action_result.data.*.priority"
                                }
                            }
                        },
                        "functionId": 1,
                        "functionName": "filter_1",
                        "id": "4",
                        "type": "filter"
                    },
                    "errors": {},
                    "id": "4",
                    "type": "filter",
                    "warnings": {},
                    "x": 1040,
                    "y": 904.5
                },
                "5": {
                    "data": {
                        "advanced": {
                            "join": []
                        },
                        "functionId": 2,
                        "functionName": "format_2",
                        "id": "5",
                        "parameters": [
                            "run_query_1:action_result.summary.total_events"
                        ],
                        "template": "There were a total of {0} events. Here is a list of high priority peers.\n",
                        "type": "format"
                    },
                    "errors": {},
                    "id": "5",
                    "type": "format",
                    "warnings": {},
                    "x": 1000,
                    "y": 1100
                },
                "6": {
                    "data": {
                        "advanced": {
                            "join": []
                        },
                        "customDatapaths": {
                            "filter_1": {
                                "condition_1:run_query_1:action_result.data.*.peer": {
                                    "contains": [],
                                    "isCustomDatapath": true,
                                    "label": "condition_1:run_query_1:action_result.data.*.peer",
                                    "value": "filtered-data:filter_1:condition_1:run_query_1:action_result.data.*.peer"
                                }
                            }
                        },
                        "functionId": 3,
                        "functionName": "format_3",
                        "id": "6",
                        "parameters": [
                            "filtered-data:filter_1:condition_1:run_query_1:action_result.data.*.peer",
                            "filtered-data:filter_1:condition_1:run_query_1:action_result.data.*.priority",
                            "filtered-data:filter_1:condition_1:run_query_1:action_result.data.*.count"
                        ],
                        "template": "%%\npeer {0} priority {1} count {2}\n%%\n",
                        "type": "format"
                    },
                    "errors": {},
                    "id": "6",
                    "type": "format",
                    "warnings": {},
                    "x": 990,
                    "y": 1284.5
                },
                "8": {
                    "data": {
                        "advanced": {
                            "join": []
                        },
                        "functionId": 4,
                        "functionName": "format_4",
                        "id": "8",
                        "parameters": [
                            "format_2:formatted_data",
                            "format_3:formatted_data"
                        ],
                        "template": "{0}\n{1}",
                        "type": "format"
                    },
                    "errors": {},
                    "id": "8",
                    "type": "format",
                    "warnings": {},
                    "x": 1000,
                    "y": 1440
                },
                "9": {
                    "data": {
                        "advanced": {
                            "join": []
                        },
                        "functionId": 2,
                        "functionName": "add_comment_2",
                        "id": "9",
                        "loop": {
                            "enabled": false,
                            "exitAfterUnit": "m",
                            "exitAfterValue": 10,
                            "exitConditionEnabled": false,
                            "exitLoopAfter": 2,
                            "pauseUnit": "m",
                            "pauseValue": 2
                        },
                        "selectMore": false,
                        "tab": "apis",
                        "type": "utility",
                        "utilities": {
                            "comment": {
                                "description": "",
                                "fields": [
                                    {
                                        "description": "",
                                        "label": "comment",
                                        "name": "comment",
                                        "placeholder": "Enter a comment",
                                        "renderType": "datapath",
                                        "required": true
                                    },
                                    {
                                        "hidden": true,
                                        "name": "container",
                                        "required": false
                                    },
                                    {
                                        "hidden": true,
                                        "name": "author",
                                        "required": false
                                    },
                                    {
                                        "hidden": true,
                                        "name": "trace",
                                        "required": false
                                    }
                                ],
                                "label": "add comment",
                                "name": "comment"
                            }
                        },
                        "utilityType": "api",
                        "values": {
                            "comment": {
                                "_internal": [
                                    "container",
                                    "author",
                                    "trace"
                                ],
                                "comment": "format_4:formatted_data"
                            }
                        }
                    },
                    "errors": {},
                    "id": "9",
                    "type": "utility",
                    "warnings": {},
                    "x": 1000,
                    "y": 1604.5
                }
            },
            "notes": ""
        },
        "input_spec": null,
        "output_spec": null,
        "playbook_type": "automation",
        "python_version": "3",
        "schema": "5.0.11",
        "version": "6.2.0.355"
    },
    "create_time": "2024-06-25T18:52:16.774270+00:00",
    "draft_mode": false,
    "labels": [
        "malware",
        "migrated_malware"
    ],
    "tags": []
}